MANIFEST.in
README.md
requirements.txt
setup.py
prediction_model/VERSION
prediction_model/__init__.py
prediction_model/pipeline.py
prediction_model/predict.py
prediction_model/training_pipeline.py
prediction_model/config/__init__.py
prediction_model/config/config.py
prediction_model/datasets/__init__.py
prediction_model/datasets/test.csv
prediction_model/datasets/train.csv
prediction_model/processing/__init__.py
prediction_model/processing/data_handling.py
prediction_model/processing/preprocessing.py
prediction_model/trained_models/__init__.py
prediction_model/trained_models/classification.pkl
prediction_model_loan.egg-info/PKG-INFO
prediction_model_loan.egg-info/SOURCES.txt
prediction_model_loan.egg-info/dependency_links.txt
prediction_model_loan.egg-info/requires.txt
prediction_model_loan.egg-info/top_level.txt
tests/pytest.ini
tests/test_prediction.py